docs/Makefile
docs/changelog.rst
docs/conf.py
docs/index.rst
docs/requirements.txt
docs/api/extract.rst
docs/api/translate.rst
ocds_babel/__init__.py
ocds_babel/extract.py
ocds_babel/translate.py
ocds_babel/translate_markdown.py
ocds_babel/translate_yaml.py
ocds_babel/util.py
ocds_babel-0.3.7.dist-info/licenses/LICENSE
ocds_babel-0.3.7.dist-info/METADATA
ocds_babel-0.3.7.dist-info/WHEEL
ocds_babel-0.3.7.dist-info/entry_points.txt
ocds_babel-0.3.7.dist-info/top_level.txt
ocds_babel-0.3.7.dist-info/RECORD
